[
null,
{"id":1,"list":[{"code":0,"indent":0,"parameters":[]}],"name":"","switchId":1,"trigger":0},
{"id":2,"list":[{"code":0,"indent":0,"parameters":[]}],"name":"","switchId":1,"trigger":0},
{"id":3,"list":[{"code":111,"indent":0,"parameters":[1,2,0,0,2]},{"code":249,"indent":1,"parameters":[{"name":"Victory1","volume":90,"pitch":100,"pan":0}]},{"code":101,"indent":1,"parameters":["",0,1,1]},{"code":401,"indent":1,"parameters":["\\TA[1]"]},{"code":401,"indent":1,"parameters":["\\>\\C[17]\\{战斗胜利!"]},{"code":401,"indent":1,"parameters":["\\|\\.\\^"]},{"code":242,"indent":1,"parameters":[1]},{"code":221,"indent":1,"parameters":[]},{"code":356,"indent":1,"parameters":["SRPGBattle End"]},{"code":117,"indent":1,"parameters":[2]},{"code":201,"indent":1,"parameters":[0,1,8,5,8,0]},{"code":222,"indent":1,"parameters":[]},{"code":0,"indent":1,"parameters":[]},{"code":412,"indent":0,"parameters":[]},{"code":111,"indent":0,"parameters":[1,1,0,0,2]},{"code":242,"indent":1,"parameters":[3]},{"code":101,"indent":1,"parameters":["Actor1",0,0,2]},{"code":401,"indent":1,"parameters":["胜败乃兵家常事，大侠请重新来过..."]},{"code":221,"indent":1,"parameters":[]},{"code":356,"indent":1,"parameters":["SRPGBattle End"]},{"code":117,"indent":1,"parameters":[2]},{"code":201,"indent":1,"parameters":[0,1,8,5,8,0]},{"code":222,"indent":1,"parameters":[]},{"code":241,"indent":1,"parameters":[{"name":"Town1","volume":90,"pitch":100,"pan":0}]},{"code":0,"indent":1,"parameters":[]},{"code":412,"indent":0,"parameters":[]},{"code":0,"indent":0,"parameters":[]}],"name":"Check game end","switchId":1,"trigger":0},
{"id":4,"list":[{"code":0,"indent":0,"parameters":[]}],"name":"","switchId":1,"trigger":0}
]